gitlab_issue_sync/__init__.py
gitlab_issue_sync/__version__.py
gitlab_issue_sync/config.py
gitlab_issue_sync/exit_codes.py
gitlab_issue_sync/git_utils.py
gitlab_issue_sync/issue_sync.py
gitlab_issue_sync/metadata_manager.py
gitlab_issue_sync/py.typed
gitlab_issue_sync/wiki.py
gitlab_issue_sync/cli/__init__.py
gitlab_issue_sync/cli/board_cmds.py
gitlab_issue_sync/cli/comment_cmd.py
gitlab_issue_sync/cli/conflicts_cmds.py
gitlab_issue_sync/cli/init_cmd.py
gitlab_issue_sync/cli/lifecycle_cmds.py
gitlab_issue_sync/cli/list_cmd.py
gitlab_issue_sync/cli/metadata_cmds.py
gitlab_issue_sync/cli/show_cmd.py
gitlab_issue_sync/cli/status_cmd.py
gitlab_issue_sync/cli/sync_cmds.py
gitlab_issue_sync/cli/wiki_cmds.py
gitlab_issue_sync/cli/display/__init__.py
gitlab_issue_sync/cli/display/board.py
gitlab_issue_sync/cli/display/conflicts.py
gitlab_issue_sync/cli/display/issue.py
gitlab_issue_sync/cli/display/metadata.py
gitlab_issue_sync/cli/display/misc.py
gitlab_issue_sync/cli/display/sync.py
gitlab_issue_sync/graphql/__init__.py
gitlab_issue_sync/graphql/client.py
gitlab_issue_sync/storage/__init__.py
gitlab_issue_sync/storage/base.py
gitlab_issue_sync/storage/config.py
gitlab_issue_sync/storage/conflicts.py
gitlab_issue_sync/storage/exceptions.py
gitlab_issue_sync/storage/issue.py
gitlab_issue_sync/storage/label.py
gitlab_issue_sync/storage/milestone.py
gitlab_issue_sync/storage/utils.py
gitlab_issue_sync/storage/work_item_types.py
gitlab_issue_sync-0.1.1.dist-info/licenses/LICENSE
gitlab_issue_sync-0.1.1.dist-info/METADATA
gitlab_issue_sync-0.1.1.dist-info/WHEEL
gitlab_issue_sync-0.1.1.dist-info/entry_points.txt
gitlab_issue_sync-0.1.1.dist-info/top_level.txt
gitlab_issue_sync-0.1.1.dist-info/RECORD
