Metadata-Version: 2.4
Name: gitlab-issue-sync
Version: 0.1.1
Summary: Sync GitLab issues with local markdown files - bidirectional synchronization for offline issue management
Author-email: Emmanuelle Delescolle <emma@levit.be>
License-Expression: MIT
Project-URL: Homepage, https://gitlab.levitnet.be/levit/glworkflow
Project-URL: Repository, https://gitlab.levitnet.be/levit/glworkflow
Project-URL: Issues, https://gitlab.levitnet.be/levit/glworkflow/-/issues
Project-URL: Documentation, https://gitlab.levitnet.be/levit/glworkflow/-/wikis/home
Keywords: gitlab,issues,sync,offline,markdown,kanban,project-management,cli,workflow
Classifier: Development Status :: 4 - Beta
Classifier: Intended Audience :: Developers
Classifier: Programming Language :: Python :: 3
Classifier: Programming Language :: Python :: 3.12
Classifier: Topic :: Software Development :: Bug Tracking
Classifier: Topic :: Software Development :: Version Control :: Git
Classifier: Environment :: Console
Classifier: Operating System :: OS Independent
Requires-Python: >=3.12
License-File: LICENSE
Requires-Dist: python-gitlab>=7.1.0
Requires-Dist: gitpython>=3.1.0
Requires-Dist: pyyaml>=6.0
Requires-Dist: click>=8.0
Requires-Dist: rich>=13.0
Requires-Dist: python-graphql-client>=0.4.3
Dynamic: license-file
